busy_gitlab/__init__.py
busy_gitlab-0.4.1.dist-info/METADATA
busy_gitlab-0.4.1.dist-info/WHEEL
busy_gitlab-0.4.1.dist-info/RECORD
