Metadata-Version: 2.1
Name: busy-gitlab
Version: 0.4.1
Summary: Busy integration plugin for GitLab issue checkboxes
License: MIT
Author: Steampunk Wizard
Author-email: busy-gitlab@wizlib.ca
Requires-Python: >=3.11,<3.12
Classifier: License :: OSI Approved :: MIT License
Classifier: Programming Language :: Python :: 3
Classifier: Programming Language :: Python :: 3.11
Requires-Dist: busy (>=7.10.2,<7.11.0)
